bozupy/__init__.py
bozupy/exception.py
bozupy/setting.py
bozupy/util.py
bozupy/cybozu/__init__.py
bozupy/cybozu/constant.py
bozupy/cybozu/dto.py
bozupy/cybozu/url.py
bozupy/cybozu/util.py
bozupy/garoon/__init__.py
bozupy/garoon/constant.py
bozupy/garoon/base/__init__.py
bozupy/garoon/base/dto.py
bozupy/garoon/notification/__init__.py
bozupy/garoon/notification/client.py
bozupy/garoon/notification/dto.py
bozupy/garoon/notification/dxo.py
bozupy/garoon/schedule/__init__.py
bozupy/garoon/schedule/client.py
bozupy/garoon/schedule/dto.py
bozupy/garoon/schedule/dxo.py
bozupy/garoon/url/__init__.py
bozupy/garoon/url/dto.py
bozupy/garoon/url/logic.py
bozupy/garoon/user/__init__.py
bozupy/garoon/user/client.py
bozupy/kintone/__init__.py
bozupy/kintone/constant.py
bozupy/kintone/util.py
bozupy/kintone/app/__init__.py
bozupy/kintone/app/client.py
bozupy/kintone/app/dto.py
bozupy/kintone/app/dxo.py
bozupy/kintone/app/graph/__init__.py
bozupy/kintone/app/graph/logic.py
bozupy/kintone/comment/__init__.py
bozupy/kintone/comment/client.py
bozupy/kintone/comment/dto.py
bozupy/kintone/comment/dxo.py
bozupy/kintone/record/__init__.py
bozupy/kintone/record/client.py
bozupy/kintone/record/dto.py
bozupy/kintone/record/dxo.py
bozupy/kintone/record/query/__init__.py
bozupy/kintone/record/query/dto.py
bozupy/kintone/record/query/logic.py
bozupy/kintone/space/__init__.py
bozupy/kintone/space/client.py
bozupy/kintone/space/dto.py
bozupy/kintone/space/dxo.py
bozupy/kintone/url/__init__.py
bozupy/kintone/url/dto.py
bozupy/kintone/url/logic.py
bozupy/slash/__init__.py
bozupy/slash/client.py
bozupy/slash/dto.py
bozupy/slash/dxo.py
bozupy-0.2.2.dist-info/licenses/LICENSE
bozupy-0.2.2.dist-info/METADATA
bozupy-0.2.2.dist-info/WHEEL
bozupy-0.2.2.dist-info/top_level.txt
bozupy-0.2.2.dist-info/RECORD
