Metadata-Version: 2.4
Name: bozupy
Version: 0.2.2
Summary: **Unofficial**: cybozu.com(kintone,Garoon,common) Python SDK
Author-email: SirTeaBear <sirteabear@gmail.com>
Requires-Python: >=3.13.0
License-File: LICENSE
Requires-Dist: lxml
Requires-Dist: python-dotenv
Requires-Dist: requests
Dynamic: license-file
